LICENSE.md
README.md
setup.py
macros/__init__.py
macros/module_reader.py
macros/plugin.py
macros/smart_image_resolver.py
macros/smart_link_resolver.py
macros/test.py
macros/reports/__init__.py
macros/reports/grafana.py
macros/reports/pingdom.py
macros/reports/zendesk.py
mkdocs_plugin_daon_macros.egg-info/PKG-INFO
mkdocs_plugin_daon_macros.egg-info/SOURCES.txt
mkdocs_plugin_daon_macros.egg-info/dependency_links.txt
mkdocs_plugin_daon_macros.egg-info/entry_points.txt
mkdocs_plugin_daon_macros.egg-info/requires.txt
mkdocs_plugin_daon_macros.egg-info/top_level.txt
tests/__init__.py
tests/test_pingdom.py
tests/test_zendesk.py