Metadata-Version: 2.1
Name: mkdocs-plugin-daon-macros
Version: 0.2.9
Summary: Unleash the power of MkDocs with macros and variables
Home-page: https://github.com/fralau/mkdocs-plugin-daon-macros
Author: Laurent Franceschetti
Author-email: info@settlenext.com
License: MIT
Keywords: mkdocs python markdown macros
Classifier: Development Status :: 5 - Production/Stable
Classifier: Intended Audience :: Developers
Classifier: Intended Audience :: Information Technology
Classifier: License :: OSI Approved :: MIT License
Classifier: Programming Language :: Python
Classifier: Programming Language :: Python :: 3 :: Only
Classifier: Programming Language :: Python :: 3.5
Requires-Python: >=3.5
License-File: LICENSE.md
